{
  "bolerocomunicacao": {
    "20251111-155321": "Instagram (Perfis): bolerocomunicacao"
  },
  "coleta_manual": {
    "20251111-162526": "Twitter (Keywords): ceara | Instagram (Perfis): opovoonline | Instagram (Keywords): ceara",
    "20251111-172815": "Twitter (Keywords): ceara | Instagram (Perfis): opovoonline | Instagram (Keywords): ceara"
  },
  "o_povo": {
    "20251113-134305": "Instagram (Perfis): opovoonline"
  },
  "diario_do_nordeste": {
    "20251113-144039": "Instagram (Perfis): diariodonordeste"
  },
  "campanha_nikolas_ferreira": {
    "20251231-181055": "Twitter (Perfis): @nikolas_dm, @metropoles, @folha, @g1 | Twitter (Keywords): nikolas stf, (from:g1 OR from:folha) nikolas, nikolas ferreira | Instagram (Perfis): nikolasferreiradm | Instagram (Keywords): nikolasferreira, pl2026",
    "20251231-192820": "Twitter (Perfis): @nikolas_dm | Twitter (Keywords): (from:g1 OR from:folha OR from:estadao) nikolas, (from:g1 OR from:folha OR from:estadao OR from:metropoles) \"nikolas ferreira\", \"deputado nikolas\", \"chupetinha\" nikolas, \"nikolas ferreira\" | Instagram (Perfis): portalg1, nikolasferreiradm, metropoles | Instagram (Keywords): nikolasferreira, nikolas, pl2026",
    "20251231-201032": "Twitter (Perfis): @nikolas_dm | Twitter (Keywords): \"chupetinha\" nikolas, (from:g1 OR from:folha OR from:estadao) nikolas, (from:g1 OR from:folha OR from:estadao OR from:metropoles) \"nikolas ferreira\", \"nikolas ferreira\", \"deputado nikolas\" | Instagram (Perfis): metropoles, nikolasferreiradm, portalg1 | Instagram (Keywords): pl2026, nikolasferreira, nikolas"
  }
}